mllb/__init__.py
mllb/activation_functions.py
mllb/convolutional_neural_network.py
mllb/dataset.py
mllb/layer_creation.py
mllb/learning_rate.py
mllb/linear_regression.py
mllb/logistic_regression.py
mllb/neural_network_layers.py
mllb-0.0.3.dist-info/LICENSE
mllb-0.0.3.dist-info/METADATA
mllb-0.0.3.dist-info/WHEEL
mllb-0.0.3.dist-info/top_level.txt
mllb-0.0.3.dist-info/RECORD
