Metadata-Version: 2.1
Name: mllb
Version: 0.0.3
Summary: Machine Learning package
Home-page: https://github.com/theiyobosa/mllb
Author: Iyobosa Evbayowieru
Author-email: theiyobosa@outlook.com
License: UNKNOWN
Platform: UNKNOWN
Classifier: Programming Language :: Python :: 3
Classifier: License :: OSI Approved :: MIT License
Classifier: Operating System :: OS Independent
Requires-Python: >=3.6
